memo/__init__.py
memo/_base.py
memo/_error.py
memo/_grid.py
memo/_http.py
memo/_runner.py
memo/_util.py
tests/__init__.py
tests/conftest.py
tests/test_docs.py
tests/test_grid.py
tests/test_memfile.py
tests/test_memlist.py
tests/test_runner.py
tests/test_skip.py
memo-0.2.4.dist-info/LICENSE
memo-0.2.4.dist-info/METADATA
memo-0.2.4.dist-info/WHEEL
memo-0.2.4.dist-info/top_level.txt
memo-0.2.4.dist-info/RECORD
