Metadata-Version: 2.2
Name: memo
Version: 0.2.4
Home-page: https://github.com/koaning/memo
Project-URL: Bug Tracker, https://github.com/koaning/memo/issues
Project-URL: Documentation, https://koaning.github.io/memo/getting-started.html
Project-URL: Source Code, https://github.com/koaning/memo
License-File: LICENSE
Requires-Dist: rich>=9.2.0
Requires-Dist: orjson>=3.4.5
Requires-Dist: joblib>=1.0.1
Provides-Extra: web
Requires-Dist: httpx>=0.16.1; extra == "web"
Requires-Dist: rich>=9.2.0; extra == "web"
Requires-Dist: orjson>=3.4.5; extra == "web"
Requires-Dist: joblib>=1.0.1; extra == "web"
Provides-Extra: test
Requires-Dist: flake8>=3.6.0; extra == "test"
Requires-Dist: pytest>=4.0.2; extra == "test"
Requires-Dist: numpy>=1.19.4; extra == "test"
Requires-Dist: mktestdocs>=0.1.0; extra == "test"
Requires-Dist: tqdm>=4.54.0; extra == "test"
Requires-Dist: pre-commit>=2.17.0; extra == "test"
Requires-Dist: rich>=9.2.0; extra == "test"
Requires-Dist: orjson>=3.4.5; extra == "test"
Requires-Dist: joblib>=1.0.1; extra == "test"
Provides-Extra: dev
Requires-Dist: jupyter>=1.0.0; extra == "dev"
Requires-Dist: jupyterlab>=0.35.4; extra == "dev"
Requires-Dist: mkdocs==1.1.2; extra == "dev"
Requires-Dist: mkdocs-material==6.1.6; extra == "dev"
Requires-Dist: mkdocstrings==0.13.6; extra == "dev"
Requires-Dist: flake8>=3.6.0; extra == "dev"
Requires-Dist: pytest>=4.0.2; extra == "dev"
Requires-Dist: numpy>=1.19.4; extra == "dev"
Requires-Dist: mktestdocs>=0.1.0; extra == "dev"
Requires-Dist: tqdm>=4.54.0; extra == "dev"
Requires-Dist: pre-commit>=2.17.0; extra == "dev"
Requires-Dist: rich>=9.2.0; extra == "dev"
Requires-Dist: orjson>=3.4.5; extra == "dev"
Requires-Dist: joblib>=1.0.1; extra == "dev"
Requires-Dist: httpx>=0.16.1; extra == "dev"
Requires-Dist: rich>=9.2.0; extra == "dev"
Requires-Dist: orjson>=3.4.5; extra == "dev"
Requires-Dist: joblib>=1.0.1; extra == "dev"
Dynamic: description
Dynamic: description-content-type
Dynamic: home-page
Dynamic: project-url
Dynamic: provides-extra
Dynamic: requires-dist
